{"singlePage": [], "startSite": "", "filingNum": "", "onePageListNum": 15, "commentLabelColor": "#006b75", "yearColorList": ["#bc4c00", "#0969da", "#1f883d", "#A333D0"], "i18n": "CN", "themeMode": "manual", "dayTheme": "light", "nightTheme": "dark", "urlMode": "pinyin", "script": "", "style": "", "bottomText": "", "showPostSource": 1, "iconList": {}, "UTC": 8, "rssSplit": "sentence", "title": "Kevin's Blog", "subTitle": "\u8fd9\u662f\u4ec0\u4e48\uff0c\u8bd5\u4e00\u4e0b", "avatarUrl": "https://github.githubassets.com/favicons/favicon.svg", "GMEEK_VERSION": "last", "postListJson": {"P1": {"htmlDir": "docs/post/xing-qiong-tie-dao- -gong-lve- -he-ji.html", "labels": ["\u65e5\u5e38"], "postTitle": "\u661f\u7a79\u94c1\u9053 \u653b\u7565 \u5408\u8f91", "postUrl": "post/xing-qiong-tie-dao-%20-gong-lve-%20-he-ji.html", "postSourceUrl": "https://github.com/AEDELSTAN/aedelstan.github.io/issues/1", "commentNum": 0, "wordCount": 51, "description": "\u9ec4\u6cc9\uff1a\r\nhttps://www.miyoushe.com/sr/article/50731532\r\n\u3002", "top": 0, "createdAt": 1712076564, "style": "", "script": "", "createdDate": "2024-04-03", "dateLabelColor": "#bc4c00"}}, "singeListJson": {}, "labelColorDict": {"documentation": "#0075ca", "duplicate": "#cfd3d7", "enhancement": "#a2eeef", "good first issue": "#7057ff", "help wanted": "#008672", "invalid": "#e4e669", "question": "#d876e3", "wontfix": "#ffffff", "\u65e5\u5e38": "#0E7BAC"}, "displayTitle": "Kevin's Blog", "faviconUrl": "https://github.githubassets.com/favicons/favicon.svg", "homeUrl": "https://AEDELSTAN.github.io/aedelstan.github.io", "prevUrl": "disabled", "nextUrl": "disabled"}